Computer Architecture/Lab 5/sr_latch.v

module sr_latch
(
input s,
input r,
output q,
output q_n
);
assign q = ~ ( r | q_n ) ;
assign q_n = ~ ( s | q ) ;
endmodule

Computer Architecture/Lab 5/testbench.v
module testbench;
reg s, r;
wire q, q_n;
sr_latch sr_latch (s, r, q, q_n) ;
initial $dumpvars ;
initial
begin
$monitor ("%0d s %b r %b q %b q_n %b " , $time , s , r , q , q_n ) ;
# 10; s = 0; r = 0;
# 10; s = 1; r = 0;
# 10; s = 0; r = 0;
# 10; s = 0; r = 1;
# 10; s = 0; r = 0;
# 10; s = 1; r = 1;
# 10; s = 0; r = 0;
# 10; s = 0; r = 0;
# 10;
$finish ;
end
endmodule

Computer Architecture/Lab 5/dump.vcd
$date
	Thu Oct 01 15:50:22 2020
$end
$version
	ModelSim Version 10.5b
$end
$timescale
	1ps
$end

$scope module testbench $end
$var reg 1 ! s $end
$var reg 1 " r $end
$var wire 1 # q $end
$var wire 1 $ q_n $end

$scope module sr_latch $end
$var wire 1 % s $end
$var wire 1 & r $end
$var wire 1 # q $end
$var wire 1 $ q_n $end
$upscope $end
$upscope $end
$enddefinitions $end
#0
$dumpvars
x!
x"
x#
x$
x&
x%
$end
#10
0!
0"
0%
0&
#20
1!
1%
0$
1#
#30
0!
0%
#40
1"
1&
0#
1$
#50
0"
0&
#60
1!
1"
1%
1&
0$
#70
0!
0"
0%
0&
1#
